setup.py
binomial_gaussian_nbk/Binomialdistribution.py
binomial_gaussian_nbk/Gaussiandistribution.py
binomial_gaussian_nbk/Generaldistribution.py
binomial_gaussian_nbk/__init__.py
binomial_gaussian_nbk.egg-info/PKG-INFO
binomial_gaussian_nbk.egg-info/SOURCES.txt
binomial_gaussian_nbk.egg-info/dependency_links.txt
binomial_gaussian_nbk.egg-info/not-zip-safe
binomial_gaussian_nbk.egg-info/top_level.txt