Metadata-Version: 1.0
Name: binomial-gaussian-nbk
Version: 1.0
Summary: Gaussian and Binomial distributions
Home-page: UNKNOWN
Author: Nishant Bhaskar
Author-email: UNKNOWN
License: UNKNOWN
Platform: UNKNOWN
